cr_mech_coli-0.9.0.dist-info/METADATA
cr_mech_coli-0.9.0.dist-info/WHEEL
cr_mech_coli-0.9.0.dist-info/entry_points.txt
cr_mech_coli-0.9.0.dist-info/licenses/LICENSE
cr_mech_coli/__init__.py
cr_mech_coli/cr_mech_coli.cpython-314-s390x-linux-gnu.so
cr_mech_coli/cr_mech_coli.pyi
cr_mech_coli/crm_amir/__init__.py
cr_mech_coli/crm_amir/crm_amir_rs.pyi
cr_mech_coli/crm_amir/main.py
cr_mech_coli/crm_divide/__init__.py
cr_mech_coli/crm_divide/main.py
cr_mech_coli/crm_estimate_params/__init__.py
cr_mech_coli/crm_estimate_params/main.py
cr_mech_coli/crm_fit/__init__.py
cr_mech_coli/crm_fit/crm_fit_rs.pyi
cr_mech_coli/crm_fit/main.py
cr_mech_coli/crm_fit/plotting.py
cr_mech_coli/crm_gen_data/__init__.py
cr_mech_coli/crm_gen_data/main.py
cr_mech_coli/crm_multilayer/__init__.py
cr_mech_coli/crm_multilayer/crm_multilayer_rs.pyi
cr_mech_coli/crm_multilayer/main.py
cr_mech_coli/crm_multilayer/plotting.py
cr_mech_coli/crm_multilayer/runner.py
cr_mech_coli/crm_perf_plots.py
cr_mech_coli/crm_save_masks.py
cr_mech_coli/datatypes.py
cr_mech_coli/fitting.py
cr_mech_coli/imaging.py
cr_mech_coli/imaging_rs.py
cr_mech_coli/plotting.py
cr_mech_coli/simulation.py
cr_mech_coli-0.9.0.dist-info/RECORD
