Metadata-Version: 2.4
Name: cr_mech_coli
Version: 0.9.0
Classifier: Programming Language :: Rust
Classifier: Programming Language :: Python :: Implementation :: CPython
Classifier: Programming Language :: Python :: Implementation :: PyPy
Requires-Dist: pyvista
Requires-Dist: numpy
Requires-Dist: opencv-python
Requires-Dist: tqdm>=4.60
Requires-Dist: scikit-image>=0.24
Requires-Dist: pytest>=8
Requires-Dist: matplotlib
License-File: LICENSE
Requires-Python: >=3.10
